LICENSE
README.md
setup.cfg
setup.py
cabul/__init__.py
cabul/client.py
cabul/errors.py
cabul/http.py
cabul/models.py
cabul.egg-info/PKG-INFO
cabul.egg-info/SOURCES.txt
cabul.egg-info/dependency_links.txt
cabul.egg-info/requires.txt
cabul.egg-info/top_level.txt