Metadata-Version: 2.1
Name: cabul
Version: 0.0.2
Summary: All the power of Cabul, RedditNSFW. This modules has a bunch feature subreddit for generating hentai stuff.
Home-page: https://github.com/sinkaroid/cabulAsync.py
Author: sinkaroid
License: MIT
Project-URL: Issue Tracker, https://github.com/sinkaroid/cabulAsync/issues
Project-URL: Source Code, https://github.com/sinkaroid/cabulAsync
Platform: UNKNOWN
Classifier: Development Status :: 2 - Pre-Alpha
Classifier: Framework :: AsyncIO
Classifier: Intended Audience :: Developers
Classifier: License :: OSI Approved :: MIT License
Classifier: Natural Language :: English
Classifier: Operating System :: OS Independent
Classifier: Programming Language :: Python :: 3.8
Classifier: Programming Language :: Python :: 3.9
Classifier: Topic :: Internet
Classifier: Topic :: Software Development :: Libraries
Classifier: Topic :: Software Development :: Libraries :: Python Modules
Classifier: Topic :: Utilities
Requires-Python: >=3.8
